xunit_tools/VERSION
xunit_tools/__init__.py
xunit_tools/render_objects.py
xunit_tools/test_objects.py
xunit_tools/xunit_diff.py
xunit_tools/xunit_parse.py
xunit_tools/templates/layout.html
xunit_tools/templates/macro.html
xunit_tools/templates/xdiff.html
xunit_tools/templates/xunit.html
xunit_tools-0.0.2.dist-info/LICENSE
xunit_tools-0.0.2.dist-info/METADATA
xunit_tools-0.0.2.dist-info/WHEEL
xunit_tools-0.0.2.dist-info/entry_points.txt
xunit_tools-0.0.2.dist-info/top_level.txt
xunit_tools-0.0.2.dist-info/RECORD
