Metadata-Version: 2.1
Name: xunit-tools
Version: 0.0.2
Summary: xunit_tools: generate HTML reports and diffs from XUnit XML files
Home-page: https://github.com/charlesthomas/xunit_tools
Author: Charles Thomas
Author-email: ch@rlesthom.as
License: MIT License
Requires-Dist: Jinja2 (==2.10)
